alpaca/__init__.py
alpaca/alpaca.py
alpaca/alpaca_dataset.py
alpaca/decoder.py
alpaca/decoder_block.py
alpaca/embedding.py
alpaca/encoder.py
alpaca/encoder_block.py
alpaca/ffn.py
alpaca/final_linear_layer.py
alpaca/multi_head_cross_attention.py
alpaca/multi_head_self_attention.py
alpaca/positional_encoding.py
alpaca/preprocessing.py
alpaca/single_head_self_attention.py
alpaca/tokenizer.py
alpaca/train.py
alpaca/transformer.py
alpaca/validate.py
alpaca_transformer-0.1.9.6.dist-info/METADATA
alpaca_transformer-0.1.9.6.dist-info/WHEEL
alpaca_transformer-0.1.9.6.dist-info/top_level.txt
alpaca_transformer-0.1.9.6.dist-info/RECORD
