Metadata-Version: 2.4
Name: alpaca-transformer
Version: 0.1.9.6
Summary: A remade version of basic transformers
Home-page: https://github.com/RazielMoesch/alpaca
Author: RazielMoesch
Author-email: RazielMoesch <razielsoccer@gmail.com>
Requires-Python: >=3.9
Dynamic: author
Dynamic: home-page
Dynamic: requires-python
